ROMtools/Animator.py
ROMtools/Configuration.py
ROMtools/Force.py
ROMtools/RigidBody.py
ROMtools/Solver.py
ROMtools/SpringDamper.py
ROMtools/__init__.py
ROMtools-0.2.5.dist-info/LICENSE
ROMtools-0.2.5.dist-info/METADATA
ROMtools-0.2.5.dist-info/WHEEL
ROMtools-0.2.5.dist-info/top_level.txt
ROMtools-0.2.5.dist-info/RECORD
