Metadata-Version: 2.1
Name: ROMtools
Version: 0.2.5
Summary: Rigid body dynamics tools for reduced order modeling of deformable systems
Home-page: https://github.com/turnerjennings/ROMtools
Author: Turner Jennings
Author-email: Turner Jennings <turner.jennings@outlook.com>
License: MIT License
Project-URL: Repository, https://github.com/turnerjennings/ROMtools.git
Project-URL: Documentation, https://turnerjennings.github.io/ROMtools/
Project-URL: Issues, https://turnerjennings.github.io/ROMtools/issues
Keywords: rigid-body-dynamics,reduced-order-modeling
Classifier: Development Status :: 3 - Alpha
Classifier: Intended Audience :: Science/Research
Classifier: License :: OSI Approved :: MIT License
Classifier: Natural Language :: English
Classifier: Topic :: Scientific/Engineering
Requires-Python: >=3.8.1
License-File: LICENSE
Requires-Dist: numpy
Requires-Dist: matplotlib
Provides-Extra: dev
Requires-Dist: pytest ; extra == 'dev'
